pytest_container/__init__.py
pytest_container/build.py
pytest_container/container.py
pytest_container/helpers.py
pytest_container/inspect.py
pytest_container/logging.py
pytest_container/plugin.py
pytest_container/pod.py
pytest_container/py.typed
pytest_container/runtime.py
pytest_container-0.4.4.dist-info/licenses/LICENSE
tests/__init__.py
tests/conftest.py
tests/images.py
tests/test_container.py
tests/test_container_build.py
tests/test_copy_from_repo.py
tests/test_env_variables.py
tests/test_git_repository_build.py
tests/test_healthcheck.py
tests/test_inspect.py
tests/test_launcher.py
tests/test_lock.py
tests/test_pod.py
tests/test_port_forwarding.py
tests/test_pytest_param.py
tests/test_runtime.py
tests/test_version.py
tests/test_volumes.py
pytest_container-0.4.4.dist-info/METADATA
pytest_container-0.4.4.dist-info/WHEEL
pytest_container-0.4.4.dist-info/entry_points.txt
pytest_container-0.4.4.dist-info/top_level.txt
pytest_container-0.4.4.dist-info/RECORD
