Metadata-Version: 2.4
Name: pytest_container
Version: 0.4.4
Summary: Pytest fixtures for writing container based tests
Home-page: https://dcermak.github.io/pytest_container/
Author: Dan Čermák
Author-email: dcermak@suse.com>
License: LGPL-2.1-or-later
Project-URL: Repository, https://github.com/dcermak/pytest_container/
Classifier: Development Status :: 4 - Beta
Classifier: Framework :: Pytest
Classifier: Intended Audience :: Developers
Classifier: License :: OSI Approved
Classifier: License :: OSI Approved :: GNU Lesser General Public License v2 or later (LGPLv2+)
Classifier: Topic :: Software Development :: Quality Assurance
Classifier: Topic :: Software Development :: Testing
License-File: LICENSE
Requires-Dist: pytest>=3.10
Requires-Dist: pytest-testinfra>=6.4.0; python_version < "3.7"
Requires-Dist: pytest-testinfra>=7.0; python_version >= "3.7" and python_version < "3.8"
Requires-Dist: pytest-testinfra>=8.0; python_version >= "3.8"
Requires-Dist: dataclasses>=0.8; python_version < "3.7"
Requires-Dist: typing-extensions<4.8,>=3.0; python_version < "3.8"
Requires-Dist: typing-extensions>=4.8; python_version <= "3.10" and python_version > "3.7"
Requires-Dist: cached-property>=1.5; python_version < "3.8"
Requires-Dist: filelock>=3.4
Requires-Dist: deprecation>=2.1
Dynamic: license-file
